mimetica/__init__.py
mimetica/gui/__init__.py
mimetica/gui/canvas.py
mimetica/gui/dock.py
mimetica/gui/image.py
mimetica/gui/main.py
mimetica/gui/plot.py
mimetica/gui/settings.py
mimetica/gui/splitview.py
mimetica/gui/tab.py
mimetica/gui/thumbnail.py
mimetica/gui/roi/__init__.py
mimetica/gui/roi/contour.py
mimetica/gui/roi/line.py
mimetica/gui/roi/target.py
mimetica/models/__init__.py
mimetica/scan/__init__.py
mimetica/scan/layer.py
mimetica/scan/stack.py
mimetica/utils/__init__.py
mimetica/utils/config.py
mimetica/utils/functions.py
mimetica/utils/logger.py
mimetica-0.2.5.post4.dist-info/METADATA
mimetica-0.2.5.post4.dist-info/WHEEL
mimetica-0.2.5.post4.dist-info/entry_points.txt
mimetica-0.2.5.post4.dist-info/top_level.txt
mimetica-0.2.5.post4.dist-info/RECORD
