Metadata-Version: 2.4
Name: mimetica
Version: 0.2.5.post4
Author-email: Alexander Hadjiivanov <43831101+cantordust@users.noreply.github.com>
License-Expression: MIT
Requires-Python: >=3.12
Requires-Dist: cloup
Requires-Dist: ipykernel
Requires-Dist: loguru
Requires-Dist: matplotlib
Requires-Dist: numpy
Requires-Dist: omegaconf
Requires-Dist: openpyxl
Requires-Dist: pandas
Requires-Dist: platformdirs
Requires-Dist: pyqtgraph
Requires-Dist: PySide6
Requires-Dist: rich
Requires-Dist: scikit-image[optional]
Requires-Dist: shapely
